{
  "sustainability_report": "EVIDENCE-BASED SUSTAINABILITY SOLUTIONS REPORT\n============================================================\n\n**ECU COMPONENT ANALYSIS**\n\nBased on the ECU sample input data:\n\n**ENVIRONMENTAL HOTSPOT PRIORITY RANKING**\n\n1. Aluminium Die Casting\n   Life Cycle Phase: production\n   Environmental Significance: high\n   Impact Category: Material Extraction and Processing\n   Impact Source: Radiator production\n   Quantitative Impact: 160.1g Aluminium\n   Priority Justification: High weight of aluminium used in radiator production\n   Description: The production of the radiator component using aluminium material through die casting may have significant environmental impacts related to material extraction and processing.\n\n2. PBT Injection Molding\n   Life Cycle Phase: production\n   Environmental Significance: medium\n   Impact Category: Material Extraction and Processing\n   Impact Source: Housing production\n   Quantitative Impact: 37.45g PBT\n   Priority Justification: Medium weight of PBT used in housing production\n   Description: The production of the housing component using PBT material through injection molding may have environmental impacts related to material extraction and processing.\n\n3. PCBA Production\n   Life Cycle Phase: production\n   Environmental Significance: medium\n   Impact Category: Material Extraction and Processing\n   Impact Source: PCBA production\n   Quantitative Impact: 40.7g PCB + 61.8g soldered components\n   Priority Justification: Medium weight of materials used in PCBA production\n   Description: The production of the PCBA component using various materials through THT and SMD soldering may have environmental impacts related to material extraction and processing.\n\n4. Steel Punching and Bending\n   Life Cycle Phase: production\n   Environmental Significance: low\n   Impact Category: Material Extraction and Processing\n   Impact Source: EMC Shield production\n   Quantitative Impact: 30.5g Steel\n   Priority Justification: Low weight of steel used in EMC Shield production\n   Description: The production of the EMC Shield component using steel material through punching and bending may have relatively low environmental impacts related to material extraction and processing.\n\n**RESEARCH-BASED SUSTAINABILITY SOLUTIONS**\n\n### Aluminium_Die_Casting\n\n**Papers with Quantitative Sustainability Data:**\n\n**Paper:** An Innovative Line Balancing for the Aluminium Melting Process (PDF: http://arxiv.org/pdf/2504.02857v1)\n\n**QUANTITATIVE FINDINGS:**\n1. 118% increase in output percentage\n2. 117.6% growth in marginal daily profit\n3. USD67,786/day net profit margin\n4. 50% increase in labor costs\n5. USD28,800 maximum profit margin per casting cycle of 36 rods\n6. USD800/rod profit margin\n7. 4.36 times/day production output after optimization\n8. 2 times/day production output before optimization\n\n**TECHNOLOGIES/METHODS:**\n1. Mixed Integer Linear Programming (MILP) for line balancing\n2. Lean Methodology for process optimization\n3. Industrial Engineering for resource allocation and layout design\n\n**PROCESS IMPROVEMENTS:**\n1. Optimization of melting furnace and melting tank operations\n2. Increased daily output rates from 2 to 4.36 cycles\n3. Reduction of idle time for melting furnaces\n4. Improved production flow through balanced workload\n\n**RELEVANCE TO Aluminium_Die_Casting:**\nAlthough the paper focuses on aluminium extrusion, the principles of line balancing, process optimization, and energy efficiency can be applied to Aluminium_Die_Casting. The paper's discussion on melting furnace optimization, temperature control, and idle time reduction may be relevant to the die casting process, which also involves melting and casting of aluminium. However, the specific quantitative findings may not be directly applicable due to differences in process characteristics and material properties. Further analysis would be required to determine the potential for adapting these optimizations to the Aluminium_Die_Casting hotspot.\n\n---\n\n**Paper:** Optimization of Solidification in Die Casting using Numerical\n  Simulations and Machine Learning (PDF: http://arxiv.org/pdf/1901.02364v2)\n\n**QUANTITATIVE FINDINGS:**\n1. Solidification time reduction: 1.99 s (achieved through optimization)\n2. Max Grain Size reduction: 22.39 Î¼m (achieved through optimization)\n3. Min Yield Strength improvement: 137.95 MPa (achieved through optimization)\n4. Temperature optimization: Initial temperature of 1015.8 K and wall temperatures ranging from 500.7 K to 643.6 K\n5. Energy consumption reduction: Not explicitly stated, but the optimization process aims to improve process efficiency\n6. Local sensitivity reduction: The chosen design has a minimal local sensitivity norm, indicating reduced sensitivity to input variations\n\n**TECHNOLOGIES/METHODS:**\n1. Numerical simulations using finite volume method\n2. Machine learning using neural networks\n3. Multi-objective optimization using NSGA-II algorithm\n4. Genetic algorithm for single-objective optimization\n\n**PROCESS IMPROVEMENTS:**\n1. Optimization of solidification process in die casting\n2. Improvement in product quality through grain size and yield strength control\n3. Reduction in solidification time, leading to increased productivity\n\n**RELEVANCE TO Aluminium_Die_Casting:**\nThe paper directly addresses the optimization of the solidification process in die casting, which is relevant to the Aluminium_Die_Casting hotspot. The optimization of initial and wall temperatures can lead to improved product quality, reduced solidification time, and increased productivity. The use of numerical simulations, machine learning, and multi-objective optimization algorithms can be applied to the Aluminium_Die_Casting process to achieve similar improvements.\n\nMATERIAL COMPATIBILITY ANALYSIS:\nThe paper focuses on aluminum alloys, which are commonly used in die casting. The optimization techniques and algorithms used can be applied to other aluminum alloys used in the Aluminium_Die_Casting hotspot.\n\nPROCESS ALIGNMENT ASSESSMENT:\nThe die casting process studied in the paper is similar to the process used in the Aluminium_Die_Casting hotspot. The optimization of solidification time, grain size, and yield strength can be directly applied to the hotspot process.\n\nQUANTITATIVE SUSTAINABILITY BENEFIT TRANSLATION:\nThe paper's optimization results can lead to a reduction in energy consumption and improved material efficiency. However, the exact quantitative sustainability benefits are not explicitly stated. Assuming a similar reduction in solidification time and energy consumption, the potential environmental benefits could be significant.\n\nTECHNOLOGY AND METHOD ADAPTATION POTENTIAL:\nThe optimization techniques and algorithms used in the paper can be directly applied to the Aluminium_Die_Casting hotspot. The use of numerical simulations, machine learning, and multi-objective optimization algorithms can help improve the sustainability of the die casting process. However, some adaptations may be necessary to account for specific material properties, equipment, and process conditions.\n\n---\n\n**Paper:** MEDPNet: Achieving High-Precision Adaptive Registration for Complex Die\n  Castings (PDF: http://arxiv.org/pdf/2403.09996v1)\n\n**QUANTITATIVE FINDINGS:**\n1. 85%: The overlap rate of point cloud data in DieCastCloud.\n2. 0.001: Learning rate of Efficient DCP.\n3. 200: Number of epochs for Efficient DCP training.\n4. 32: Train batch size for Efficient DCP.\n5. 10: Train batch size for Efficient DCP.\n6. 4.822984: Mean Squared Error (MSE) for rotation angles of Efficient DCP.\n7. 0.000231: Mean Squared Error (MSE) for translation directions of Efficient DCP.\n8. 2.196129: Root Mean Squared Error (RMSE) for rotation angles of Efficient DCP.\n9. 0.015187: Root Mean Squared Error (RMSE) for translation directions of Efficient DCP.\n10. 1.350260: Mean Absolute Error (MAE) for rotation angles of Efficient DCP.\n11. 0.008338: Mean Absolute Error (MAE) for translation directions of Efficient DCP.\n12. 0.128: Root Mean Square Error (RMSE) in millimeters for SAC-IA on clean data.\n13. 47.64: Registration time in seconds for SAC-IA on clean data.\n14. 0.206: Root Mean Square Error (RMSE) in millimeters for SAC-IA on noisy data.\n15. 53.76: Registration time in seconds for SAC-IA on noisy data.\n16. 0.168: Root Mean Square Error (RMSE) in millimeters for 4PCS on clean data.\n17. 13.32: Registration time in seconds for 4PCS on clean data.\n18. 0.273: Root Mean Square Error (RMSE) in millimeters for 4PCS on noisy data.\n19. 16.11: Registration time in seconds for 4PCS on noisy data.\n20. 0.158: Root Mean Square Error (RMSE) in millimeters for NDT on clean data.\n21. 4.33: Registration time in seconds for NDT on clean data.\n22. 0.182: Root Mean Square Error (RMSE) in millimeters for NDT on noisy data.\n23. 5.64: Registration time in seconds for NDT on noisy data.\n24. 0.153: Root Mean Square Error (RMSE) in millimeters for ICP on clean data.\n25. 12.47: Registration time in seconds for ICP on clean data.\n26. 0.197: Root Mean Square Error (RMSE) in millimeters for ICP on noisy data.\n27. 18.12: Registration time in seconds for ICP on noisy data.\n28. 0.092: Root Mean Square Error (RMSE) in millimeters for MDR on clean data.\n29. 25.92: Registration time in seconds for MDR on clean data.\n30. 0.148: Root Mean Square Error (RMSE) in millimeters for MDR on noisy data.\n31. 29.41: Registration time in seconds for MDR on noisy data.\n32. 6.84315: Root Mean Square Error (RMSE) for PointNetLK on clean data.\n33. 15.9744: Root Mean Square Error (RMSE) for PointNetLK on noisy data.\n34. 4.85126: Root Mean Square Error (RMSE) for DCP on clean data.\n35. 5.87391: Root Mean Square Error (RMSE) for DCP on noisy data.\n36. 4.27784: Root Mean Square Error (RMSE) for NDT on clean data.\n37. 9.76239: Root Mean Square Error (RMSE) for NDT on noisy data.\n38. 2.19618: Root Mean Square Error (RMSE) for Efficient DCP on clean data.\n39. 3.71646: Root Mean Square Error (RMSE) for Efficient DCP on noisy data.\n40. 2.07729: Root Mean Square Error (RMSE) for ICP on clean data.\n41. 6.73248: Root Mean Square Error (RMSE) for ICP on noisy data.\n42. 1.94877: Root Mean Square Error (RMSE) for MDR on clean data.\n43. 4.67442: Root Mean Square Error (RMSE) for MDR on noisy data.\n44. 1.17245: Root Mean Square Error (RMSE) for MEDPNet on clean data.\n45. 1.32954: Root Mean Square Error (RMSE) for MEDPNet on noisy data.\n\n**TECHNOLOGIES/METHODS:**\n1. Efficient Attention\n2. Multiscale feature fusion dual-channel registration (MDR)\n3. Deep Closest Point (DCP)\n4. PointNetLK\n5. GeoTransformer\n6. PRNet\n7. DeepGMR\n8. Iterative Closest Point (ICP)\n9. Normal Distributions Transform (NDT)\n10. MEDPNet (Multimodal Efficient Deep Closest Point)\n\n**PROCESS IMPROVEMENTS:**\n1. Coarse registration using Efficient DCP\n2. Fine registration using MDR\n3. Multiscale feature fusion\n4. Dual-channel fusion module\n\n**RELEVANCE TO Aluminium_Die_Casting:**\nThe paper presents a method for high-precision adaptive registration for complex die castings, which is directly relevant to the Aluminium_Die_Casting hotspot. The method, called MEDPNet, achieves high-quality registration results by initially applying Efficient DCP for coarse registration of unaligned point cloud pairs, followed by fine-tuning through MDR. The paper provides quantitative results for various methods, including Efficient DCP, MDR, and MEDPNet, which can be applied to the Aluminium_Die_Casting hotspot to improve registration accuracy and reduce environmental impact.\n\nMATERIAL COMPATIBILITY ANALYSIS:\nThe paper does not specifically mention Aluminium_Die_Casting materials, but it does discuss die-cast parts, which can be made of aluminium. The methods presented in the paper can be applied to various materials, including aluminium.\n\nPROCESS ALIGNMENT ASSESSMENT:\nThe paper discusses point cloud registration, which is a process that can be applied to various manufacturing processes, including die casting. The methods presented in the paper can be used to improve registration accuracy and reduce environmental impact in the Aluminium_Die_Casting hotspot.\n\nQUANTITATIVE SUSTAINABILITY BENEFIT TRANSLATION:\nThe paper provides quantitative results for various methods, including Efficient DCP, MDR, and MEDPNet. These results can be used to estimate the potential environmental benefits of applying these methods to the Aluminium_Die_Casting hotspot. For example, the paper reports a Root Mean Square Error (RMSE) of 1.17245 for MEDPNet on clean data, which can be used to estimate the potential reduction in environmental impact.\n\nTECHNOLOGY AND METHOD ADAPTATION POTENTIAL:\nThe methods presented in the paper can be adapted to the Aluminium_Die_Casting hotspot with minimal modifications. The paper provides a framework for high-precision adaptive registration, which can be applied to various manufacturing processes, including die casting. The methods can be used to improve registration accuracy and reduce environmental impact in the Aluminium_Die_Casting hotspot.\n\n---\n\n\n### PBT_Injection_Molding\n\n**Papers without Specific Quantitative Data:**\n\n**Paper:** Recy-ctronics: Designing Fully Recyclable Electronics With Varied Form\n  Factors (PDF: http://arxiv.org/pdf/2406.09611v1)\n\nNo specific quantitative sustainability improvements were found in this paper.\n\n**Paper:** Space debris through the prism of the environmental performance of space\n  systems: the case of Sentinel-3 redesigned mission (PDF: http://arxiv.org/pdf/2207.06306v1)\n\nNo specific quantitative sustainability improvements were found in this paper.\n\n**Paper:** The environmental value of transport infrastructure in the UK: an\n  EXIOBASE analysis (PDF: http://arxiv.org/pdf/2504.20098v1)\n\nNo specific quantitative sustainability improvements were found in this paper.\n\n\n### PCBA_Production\n\n**Papers with Quantitative Sustainability Data:**\n\n**Paper:** Recyclable vitrimer-based printed circuit board for circular electronics (PDF: http://arxiv.org/pdf/2308.12496v1)\n\n**QUANTITATIVE FINDINGS:**\n\n1. 98% recovery of the vitrimer polymer\n2. 100% recovery of glass fibers\n3. 91% recovery of the solvent (THF)\n4. 47.9% improvement in global warming potential\n5. 65.5% improvement in ozone depletion potential\n6. 80.9% improvement in human cancer toxicity emissions\n7. 35.8% reduction in acidification\n8. 59.1% reduction in freshwater ecotoxicity\n9. 61.8% reduction in human non-cancer toxicity emissions\n10. 38.0% reduction in particulate matter\n11. 45.9% reduction in photochemical ozone\n12. 40.2% reduction in fossil depletion\n13. 79.2% reduction in mineral and metal use\n14. 28.1% reduction in water use\n15. 20.0% reduction in global warming potential for vPCB freight\n16. 28.0% reduction in ozone depletion potential for vPCB freight\n17. 14.0% reduction in fossil depletion for vPCB freight\n18. 26.0% reduction in mineral and metal use for vPCB freight\n\n**TECHNOLOGIES/METHODS:**\n\n1. Vitrimer-based printed circuit board (vPCB) fabrication\n2. Transesterification vitrimer synthesis\n3. Swelling-based separation for vitrimer composite recycling\n4. Dynamic mechanical analysis\n5. Fourier-transform infrared (FTIR) spectroscopy\n\n**PROCESS IMPROVEMENTS:**\n\n1. Temperature optimization for vitrimer synthesis\n2. Pressure optimization for vitrimer synthesis\n3. Solvent selection for vitrimer recycling (THF)\n4. Recycling process for vPCB\n\n**RELEVANCE TO PCBA_Production:**\n\nThe paper's findings on vitrimer-based printed circuit board (vPCB) fabrication and recycling have direct relevance to the PCBA_Production hotspot. The use of vPCBs could reduce the environmental impact of PCBA production by:\n\n* Reducing energy consumption: The paper's findings on temperature optimization and solvent selection could lead to energy savings in the production process.\n* Reducing material waste: The paper's findings on 98% recovery of the vitrimer polymer and 100% recovery of glass fibers could reduce material waste in the production process.\n* Reducing environmental impact: The paper's findings on improvements in global warming potential, ozone depletion potential, and human cancer toxicity emissions could reduce the overall environmental impact of PCBA production.\n\nThe technology and methods used in the paper, such as vitrimer synthesis and swelling-based separation, could be directly applied to the PCBA_Production hotspot. However, further research would be needed to adapt these technologies to the specific materials and processes used in PCBA production.\n\n---\n\n**Paper:** PCB Renewal: Iterative Reuse of PCB Substrates for Sustainable\n  Electronic Making (PDF: http://arxiv.org/pdf/2502.13255v1)\n\n**QUANTITATIVE FINDINGS:**\n\n1. 98.4% reduction in material cost for the first iteration of the camera roller PCB.\n2. 6402.90mg of FR-4 saved in the first iteration of the camera roller PCB.\n3. 71.91kJ of energy saved in the first iteration of the camera roller PCB.\n4. 15.25 minutes of fabrication time saved in the first iteration of the camera roller PCB.\n5. 4.06mg of silver epoxy consumed in the first iteration of the camera roller PCB.\n6. 74.6% reduction in material cost for the WiFi radio PCB.\n7. 5602.15mg of FR-4 saved in the WiFi radio PCB.\n8. 32.03kJ of energy saved in the WiFi radio PCB.\n9. 105mg of silver epoxy consumed in the WiFi radio PCB.\n10. 3.89 minutes longer fabrication time for the WiFi radio PCB compared to creating a new PCB.\n11. 87.5% reduction in material cost for the ESPBoy game console PCB.\n12. 5608.24mg of FR-4 saved in the ESPBoy game console PCB.\n13. 25.99kJ of energy saved in the ESPBoy game console PCB.\n14. 98.91mg of silver epoxy consumed in the ESPBoy game console PCB.\n15. Less than 5 minutes difference in fabrication time for the ESPBoy game console PCB compared to creating a new PCB.\n\n**TECHNOLOGIES/METHODS:**\n\n1. PCB Renewal technique for iterative reuse of PCB substrates.\n2. Conductive epoxy for filling isolation grooves and creating new conductive traces.\n3. CNC milling machine for engraving and modifying PCB substrates.\n4. Laser cutter for removing solder mask and creating deposition stencils.\n5. KiCAD software for designing and comparing PCB layouts.\n6. Custom EDA software plug-in for guiding epoxy deposition, generating updated profiles, and calculating resource usage.\n\n**PROCESS IMPROVEMENTS:**\n\n1. Reduced material waste through iterative reuse of PCB substrates.\n2. Decreased energy consumption by re-engraving existing PCB substrates instead of creating new ones.\n3. Improved fabrication efficiency by automating epoxy deposition and curing processes.\n4. Enhanced design flexibility through the ability to modify and update existing PCB layouts.\n\n**RELEVANCE TO PCBA_Production:**\n\nThe paper's findings on PCB Renewal and its applications in iterative reuse of PCB substrates have strong relevance to the PCBA_Production hotspot. The technique's ability to reduce material waste, energy consumption, and fabrication time can be directly applied to the production of printed circuit boards. The use of conductive epoxy and CNC milling machines can be adapted to various PCB production processes, including those used in PCBA_Production. The custom EDA software plug-in can also be integrated into existing design and manufacturing workflows to optimize resource usage and reduce environmental impact.\n\nThe quantitative benefits of PCB Renewal, such as the 98.4% reduction in material cost and 71.91kJ of energy saved, can be translated to the PCBA_Production hotspot by considering the material quantities and significance level of the production process. For example, if the hotspot produces 1000 PCBs per day, the application of PCB Renewal could potentially reduce material waste by 6402.90mg per PCB, resulting in a significant environmental impact reduction. Similarly, the energy savings of 71.91kJ per PCB could be scaled up to the entire production process, leading to substantial reductions in energy consumption and greenhouse gas emissions.\n\n---\n\n**Papers without Specific Quantitative Data:**\n\n**Paper:** Sustainable bioplastics from amyloid fibril-biodegradable polymer blends (PDF: http://arxiv.org/pdf/2105.14287v1)\n\nNo specific quantitative sustainability improvements were found in this paper.\n\n\n### Steel_Punching_and_Bending\n\n**Papers with Quantitative Sustainability Data:**\n\n**Paper:** Anisotropic behaviour law for sheets used in stamping: A comparative\n  study of steel and aluminium (PDF: http://arxiv.org/pdf/0801.3018v1)\n\n**QUANTITATIVE FINDINGS:**\n- 30-40% reduction in weight can be expected when using aluminium instead of steel.\n\n**TECHNOLOGIES/METHODS:**\n- Stamping of thin aluminium sheets\n- Quadratic non-centered Hillâs (1948) yield criterion\n- Mixed hardening law (kinematic and isotropic)\n\n**PROCESS IMPROVEMENTS:**\n- None explicitly stated in terms of process improvements with measurable results.\n\n**RELEVANCE TO Steel_Punching_and_Bending:**\nThe paper's focus on the anisotropic behavior law for sheets used in stamping, comparing steel and aluminium, has some relevance to the Steel_Punching_and_Bending hotspot. \n\n1. **MATERIAL COMPATIBILITY ANALYSIS:**\n   - The paper studies steel and aluminium, which includes the material of interest for the Steel_Punching_and_Bending hotspot (steel).\n   - Steel is directly relevant, but the paper's primary focus on aluminium for weight reduction suggests a potential application in reducing the environmental impact of steel punching and bending by considering alternative materials.\n\n2. **PROCESS ALIGNMENT ASSESSMENT:**\n   - The manufacturing process investigated (stamping) is similar to punching and bending in terms of shaping metal sheets.\n   - However, the specific conditions (temperature, pressure, cycle times) are not directly compared or optimized in the paper for steel punching and bending.\n\n3. **QUANTITATIVE SUSTAINABILITY BENEFIT TRANSLATION:**\n   - The 30-40% weight reduction potential by using aluminium instead of steel could imply a significant reduction in material usage and potentially in energy consumption for processing, given that less material needs to be manipulated.\n   - However, this benefit is more directly applicable to scenarios where material substitution is feasible rather than optimizing the steel punching and bending process itself.\n\n4. **TECHNOLOGY AND METHOD ADAPTATION POTENTIAL:**\n   - The mixed hardening law and the quadratic non-centered Hillâs yield criterion could potentially be adapted for optimizing steel punching and bending processes, especially in understanding and predicting material behavior under different loading conditions.\n   - However, the paper does not provide a direct method for reducing energy consumption, waste, or environmental impact specifically in steel punching and bending.\n\nGiven the indirect application of the paper's findings to the Steel_Punching_and_Bending hotspot, the relevance is considered weak. The primary benefit discussed (weight reduction through material substitution) does not directly address process optimizations for steel punching and bending.\n\n---\n\n**Paper:** 475Â°C aging embrittlement of partially recrystallized FeCrAl ODS\n  ferritic steels after simulated tube process (PDF: http://arxiv.org/pdf/2310.13842v2)\n\n**QUANTITATIVE FINDINGS:**\n\n1. 30% reduction in total elongation in steels after full tubing routine compared to as-extruded ones.\n2. 25% to 50% reduction of yield stress after fully recrystallization.\n3. 50% thickness reduction in each cold rolling cycle.\n4. 100MPa reduction in yield stress of STPed SP2 compared to as-extruded steel.\n5. 2000 hrs and 10000 hrs aging times for the STPed steels.\n6. 475 Â°C aging temperature.\n7. 0.3 mm thickness of the STPed plates.\n8. 4 mm initial sample thickness.\n9. 1/3 reduction of ductility in the as-extruded steels after aging.\n\n**TECHNOLOGIES/METHODS:**\n\n1. Simulated tube processing (STP)\n2. Cold rolling and heat treatment (CR-HT)\n3. Transmission electron microscopy (TEM)\n4. Electron Back Scatter Diffraction (EBSD)\n5. Mechanical alloying method\n6. Uniaxial tensile test\n\n**PROCESS IMPROVEMENTS:**\n\n1. Recrystallization treatment to reduce yield strength of ODS steels during tubing.\n2. Optimization of composition of FeCrAl steels to satisfy both oxidation resistance and low aging rate.\n\n**RELEVANCE TO Steel_Punching_and_Bending:**\n\nThe paper's findings on the aging embrittlement of partially recrystallized FeCrAl ODS ferritic steels after simulated tube processing have limited direct relevance to the Steel_Punching_and_Bending hotspot. However, the study's focus on optimizing material properties and processing conditions to improve sustainability metrics (e.g., reducing energy consumption, increasing material efficiency) could be applied to the Steel_Punching_and_Bending process.\n\nMATERIAL COMPATIBILITY ANALYSIS:\nThe paper studies FeCrAl ODS ferritic steels, which may not be directly applicable to the Steel_Punching_and_Bending hotspot. However, the principles of optimizing material properties and processing conditions could be transferred to other steel alloys used in punching and bending operations.\n\nPROCESS ALIGNMENT ASSESSMENT:\nThe simulated tube processing and cold rolling techniques used in the paper may not be directly applicable to the Steel_Punching_and_Bending process. However, the study's focus on optimizing processing conditions (e.g., temperature, thickness reduction) could be relevant to improving the sustainability of punching and bending operations.\n\nQUANTITATIVE SUSTAINABILITY BENEFIT TRANSLATION:\nThe paper's findings on the reduction of total elongation and yield stress could be translated to potential energy savings and reduced material waste in the Steel_Punching_and_Bending process. However, the exact quantitative benefits would depend on the specific material properties and processing conditions used in the hotspot.\n\nTECHNOLOGY AND METHOD ADAPTATION POTENTIAL:\nThe optimization techniques used in the paper (e.g., recrystallization treatment, composition optimization) could be adapted to the Steel_Punching_and_Bending process. However, the feasibility of these adaptations would depend on the specific material properties and processing conditions used in the hotspot.\n\n---\n\n**Papers without Specific Quantitative Data:**\n\n**Paper:** Fast Privacy-Preserving Punch Cards (PDF: http://arxiv.org/pdf/2006.06079v3)\n\nNo specific quantitative sustainability improvements were found in this paper.\n\n\n**DATA QUALITY ASSESSMENT**\n\nTotal papers analyzed: 12\nPapers with quantitative sustainability data: 7\nPapers without quantitative data: 5\n\n**REPORT DISCLAIMER**\n\nThis report is based exclusively on:\n1. Actual data from the ECU component specification\n2. Quantitative findings explicitly stated in research papers\n3. No estimates, assumptions, or generic industry values were used\n\nAll sustainability solutions are evidence-based and sourced from\nthe analyzed research literature. Where no quantitative data was\navailable, this is clearly stated.",
  "hotspot_analyses": {
    "Aluminium_Die_Casting": [
      {
        "hotspot_name": "Aluminium_Die_Casting",
        "paper_title": "An Innovative Line Balancing for the Aluminium Melting Process",
        "paper_metadata": {
          "filename": "An Innovative Line Balancing for the Aluminium Melting Process.pdf",
          "hotspot_name": "Aluminium_Die_Casting",
          "title": "An Innovative Line Balancing for the Aluminium Melting Process",
          "published_date": "2025-03-29T14:31:33Z",
          "pdf_link": "http://arxiv.org/pdf/2504.02857v1",
          "query": "aluminium die casting energy efficiency optimization"
        },
        "analysis_content": "**QUANTITATIVE FINDINGS:**\n1. 118% increase in output percentage\n2. 117.6% growth in marginal daily profit\n3. USD67,786/day net profit margin\n4. 50% increase in labor costs\n5. USD28,800 maximum profit margin per casting cycle of 36 rods\n6. USD800/rod profit margin\n7. 4.36 times/day production output after optimization\n8. 2 times/day production output before optimization\n\n**TECHNOLOGIES/METHODS:**\n1. Mixed Integer Linear Programming (MILP) for line balancing\n2. Lean Methodology for process optimization\n3. Industrial Engineering for resource allocation and layout design\n\n**PROCESS IMPROVEMENTS:**\n1. Optimization of melting furnace and melting tank operations\n2. Increased daily output rates from 2 to 4.36 cycles\n3. Reduction of idle time for melting furnaces\n4. Improved production flow through balanced workload\n\n**RELEVANCE TO Aluminium_Die_Casting:**\nAlthough the paper focuses on aluminium extrusion, the principles of line balancing, process optimization, and energy efficiency can be applied to Aluminium_Die_Casting. The paper's discussion on melting furnace optimization, temperature control, and idle time reduction may be relevant to the die casting process, which also involves melting and casting of aluminium. However, the specific quantitative findings may not be directly applicable due to differences in process characteristics and material properties. Further analysis would be required to determine the potential for adapting these optimizations to the Aluminium_Die_Casting hotspot.",
        "has_quantitative_data": true
      },
      {
        "hotspot_name": "Aluminium_Die_Casting",
        "paper_title": "Optimization of Solidification in Die Casting using Numerical\n  Simulations and Machine Learning",
        "paper_metadata": {
          "filename": "Optimization of Solidification in Die Casting using Numerical Simulations and Ma.pdf",
          "hotspot_name": "Aluminium_Die_Casting",
          "title": "Optimization of Solidification in Die Casting using Numerical\n  Simulations and Machine Learning",
          "published_date": "2019-01-08T15:28:33Z",
          "pdf_link": "http://arxiv.org/pdf/1901.02364v2",
          "query": "aluminium die casting energy efficiency optimization"
        },
        "analysis_content": "**QUANTITATIVE FINDINGS:**\n1. Solidification time reduction: 1.99 s (achieved through optimization)\n2. Max Grain Size reduction: 22.39 Î¼m (achieved through optimization)\n3. Min Yield Strength improvement: 137.95 MPa (achieved through optimization)\n4. Temperature optimization: Initial temperature of 1015.8 K and wall temperatures ranging from 500.7 K to 643.6 K\n5. Energy consumption reduction: Not explicitly stated, but the optimization process aims to improve process efficiency\n6. Local sensitivity reduction: The chosen design has a minimal local sensitivity norm, indicating reduced sensitivity to input variations\n\n**TECHNOLOGIES/METHODS:**\n1. Numerical simulations using finite volume method\n2. Machine learning using neural networks\n3. Multi-objective optimization using NSGA-II algorithm\n4. Genetic algorithm for single-objective optimization\n\n**PROCESS IMPROVEMENTS:**\n1. Optimization of solidification process in die casting\n2. Improvement in product quality through grain size and yield strength control\n3. Reduction in solidification time, leading to increased productivity\n\n**RELEVANCE TO Aluminium_Die_Casting:**\nThe paper directly addresses the optimization of the solidification process in die casting, which is relevant to the Aluminium_Die_Casting hotspot. The optimization of initial and wall temperatures can lead to improved product quality, reduced solidification time, and increased productivity. The use of numerical simulations, machine learning, and multi-objective optimization algorithms can be applied to the Aluminium_Die_Casting process to achieve similar improvements.\n\nMATERIAL COMPATIBILITY ANALYSIS:\nThe paper focuses on aluminum alloys, which are commonly used in die casting. The optimization techniques and algorithms used can be applied to other aluminum alloys used in the Aluminium_Die_Casting hotspot.\n\nPROCESS ALIGNMENT ASSESSMENT:\nThe die casting process studied in the paper is similar to the process used in the Aluminium_Die_Casting hotspot. The optimization of solidification time, grain size, and yield strength can be directly applied to the hotspot process.\n\nQUANTITATIVE SUSTAINABILITY BENEFIT TRANSLATION:\nThe paper's optimization results can lead to a reduction in energy consumption and improved material efficiency. However, the exact quantitative sustainability benefits are not explicitly stated. Assuming a similar reduction in solidification time and energy consumption, the potential environmental benefits could be significant.\n\nTECHNOLOGY AND METHOD ADAPTATION POTENTIAL:\nThe optimization techniques and algorithms used in the paper can be directly applied to the Aluminium_Die_Casting hotspot. The use of numerical simulations, machine learning, and multi-objective optimization algorithms can help improve the sustainability of the die casting process. However, some adaptations may be necessary to account for specific material properties, equipment, and process conditions.",
        "has_quantitative_data": true
      },
      {
        "hotspot_name": "Aluminium_Die_Casting",
        "paper_title": "MEDPNet: Achieving High-Precision Adaptive Registration for Complex Die\n  Castings",
        "paper_metadata": {
          "filename": "MEDPNet_ Achieving High-Precision Adaptive Registration for Complex Die Castings.pdf",
          "hotspot_name": "Aluminium_Die_Casting",
          "title": "MEDPNet: Achieving High-Precision Adaptive Registration for Complex Die\n  Castings",
          "published_date": "2024-03-15T03:42:38Z",
          "pdf_link": "http://arxiv.org/pdf/2403.09996v1",
          "query": "aluminium die casting energy efficiency optimization"
        },
        "analysis_content": "**QUANTITATIVE FINDINGS:**\n1. 85%: The overlap rate of point cloud data in DieCastCloud.\n2. 0.001: Learning rate of Efficient DCP.\n3. 200: Number of epochs for Efficient DCP training.\n4. 32: Train batch size for Efficient DCP.\n5. 10: Train batch size for Efficient DCP.\n6. 4.822984: Mean Squared Error (MSE) for rotation angles of Efficient DCP.\n7. 0.000231: Mean Squared Error (MSE) for translation directions of Efficient DCP.\n8. 2.196129: Root Mean Squared Error (RMSE) for rotation angles of Efficient DCP.\n9. 0.015187: Root Mean Squared Error (RMSE) for translation directions of Efficient DCP.\n10. 1.350260: Mean Absolute Error (MAE) for rotation angles of Efficient DCP.\n11. 0.008338: Mean Absolute Error (MAE) for translation directions of Efficient DCP.\n12. 0.128: Root Mean Square Error (RMSE) in millimeters for SAC-IA on clean data.\n13. 47.64: Registration time in seconds for SAC-IA on clean data.\n14. 0.206: Root Mean Square Error (RMSE) in millimeters for SAC-IA on noisy data.\n15. 53.76: Registration time in seconds for SAC-IA on noisy data.\n16. 0.168: Root Mean Square Error (RMSE) in millimeters for 4PCS on clean data.\n17. 13.32: Registration time in seconds for 4PCS on clean data.\n18. 0.273: Root Mean Square Error (RMSE) in millimeters for 4PCS on noisy data.\n19. 16.11: Registration time in seconds for 4PCS on noisy data.\n20. 0.158: Root Mean Square Error (RMSE) in millimeters for NDT on clean data.\n21. 4.33: Registration time in seconds for NDT on clean data.\n22. 0.182: Root Mean Square Error (RMSE) in millimeters for NDT on noisy data.\n23. 5.64: Registration time in seconds for NDT on noisy data.\n24. 0.153: Root Mean Square Error (RMSE) in millimeters for ICP on clean data.\n25. 12.47: Registration time in seconds for ICP on clean data.\n26. 0.197: Root Mean Square Error (RMSE) in millimeters for ICP on noisy data.\n27. 18.12: Registration time in seconds for ICP on noisy data.\n28. 0.092: Root Mean Square Error (RMSE) in millimeters for MDR on clean data.\n29. 25.92: Registration time in seconds for MDR on clean data.\n30. 0.148: Root Mean Square Error (RMSE) in millimeters for MDR on noisy data.\n31. 29.41: Registration time in seconds for MDR on noisy data.\n32. 6.84315: Root Mean Square Error (RMSE) for PointNetLK on clean data.\n33. 15.9744: Root Mean Square Error (RMSE) for PointNetLK on noisy data.\n34. 4.85126: Root Mean Square Error (RMSE) for DCP on clean data.\n35. 5.87391: Root Mean Square Error (RMSE) for DCP on noisy data.\n36. 4.27784: Root Mean Square Error (RMSE) for NDT on clean data.\n37. 9.76239: Root Mean Square Error (RMSE) for NDT on noisy data.\n38. 2.19618: Root Mean Square Error (RMSE) for Efficient DCP on clean data.\n39. 3.71646: Root Mean Square Error (RMSE) for Efficient DCP on noisy data.\n40. 2.07729: Root Mean Square Error (RMSE) for ICP on clean data.\n41. 6.73248: Root Mean Square Error (RMSE) for ICP on noisy data.\n42. 1.94877: Root Mean Square Error (RMSE) for MDR on clean data.\n43. 4.67442: Root Mean Square Error (RMSE) for MDR on noisy data.\n44. 1.17245: Root Mean Square Error (RMSE) for MEDPNet on clean data.\n45. 1.32954: Root Mean Square Error (RMSE) for MEDPNet on noisy data.\n\n**TECHNOLOGIES/METHODS:**\n1. Efficient Attention\n2. Multiscale feature fusion dual-channel registration (MDR)\n3. Deep Closest Point (DCP)\n4. PointNetLK\n5. GeoTransformer\n6. PRNet\n7. DeepGMR\n8. Iterative Closest Point (ICP)\n9. Normal Distributions Transform (NDT)\n10. MEDPNet (Multimodal Efficient Deep Closest Point)\n\n**PROCESS IMPROVEMENTS:**\n1. Coarse registration using Efficient DCP\n2. Fine registration using MDR\n3. Multiscale feature fusion\n4. Dual-channel fusion module\n\n**RELEVANCE TO Aluminium_Die_Casting:**\nThe paper presents a method for high-precision adaptive registration for complex die castings, which is directly relevant to the Aluminium_Die_Casting hotspot. The method, called MEDPNet, achieves high-quality registration results by initially applying Efficient DCP for coarse registration of unaligned point cloud pairs, followed by fine-tuning through MDR. The paper provides quantitative results for various methods, including Efficient DCP, MDR, and MEDPNet, which can be applied to the Aluminium_Die_Casting hotspot to improve registration accuracy and reduce environmental impact.\n\nMATERIAL COMPATIBILITY ANALYSIS:\nThe paper does not specifically mention Aluminium_Die_Casting materials, but it does discuss die-cast parts, which can be made of aluminium. The methods presented in the paper can be applied to various materials, including aluminium.\n\nPROCESS ALIGNMENT ASSESSMENT:\nThe paper discusses point cloud registration, which is a process that can be applied to various manufacturing processes, including die casting. The methods presented in the paper can be used to improve registration accuracy and reduce environmental impact in the Aluminium_Die_Casting hotspot.\n\nQUANTITATIVE SUSTAINABILITY BENEFIT TRANSLATION:\nThe paper provides quantitative results for various methods, including Efficient DCP, MDR, and MEDPNet. These results can be used to estimate the potential environmental benefits of applying these methods to the Aluminium_Die_Casting hotspot. For example, the paper reports a Root Mean Square Error (RMSE) of 1.17245 for MEDPNet on clean data, which can be used to estimate the potential reduction in environmental impact.\n\nTECHNOLOGY AND METHOD ADAPTATION POTENTIAL:\nThe methods presented in the paper can be adapted to the Aluminium_Die_Casting hotspot with minimal modifications. The paper provides a framework for high-precision adaptive registration, which can be applied to various manufacturing processes, including die casting. The methods can be used to improve registration accuracy and reduce environmental impact in the Aluminium_Die_Casting hotspot.",
        "has_quantitative_data": true
      }
    ],
    "PBT_Injection_Molding": [
      {
        "hotspot_name": "PBT_Injection_Molding",
        "paper_title": "Recy-ctronics: Designing Fully Recyclable Electronics With Varied Form\n  Factors",
        "paper_metadata": {
          "filename": "Recy-ctronics_ Designing Fully Recyclable Electronics With Varied Form Factors.pdf",
          "hotspot_name": "PBT_Injection_Molding",
          "title": "Recy-ctronics: Designing Fully Recyclable Electronics With Varied Form\n  Factors",
          "published_date": "2024-06-13T22:43:47Z",
          "pdf_link": "http://arxiv.org/pdf/2406.09611v1",
          "query": "PBT injection molding LCA environmental impact"
        },
        "analysis_content": "**QUANTITATIVE FINDINGS:**\n1. 97.5% recycling rate for LM in sheet form factor\n2. 96.1% recycling rate for LM in foam form factor\n3. 98.6% recycling rate for LM in tube form factor\n4. 87.4% recycling rate for PVA in sheet form factor\n5. 78.1% recycling rate for PVA in foam form factor\n6. 83.2% recycling rate for PVA in tube form factor\n7. 0.013Â±0.002Î©/ð ð sheet resistance\n8. 0.019Â±0.011Î©/ð ð recycled LM resistance\n9. 50% strain results in a resistance increase from approximately 0.74 Î© to 0.82 Î© for stretchable LM-filled tubes\n10. 17.4 grams of LM recovered from a batch of devices accumulated over two months\n\n**TECHNOLOGIES/METHODS:**\n1. Screen printing for patterning circuits\n2. Mechanical stirring for preparing PVA solution\n3. Mold casting for creating tubes\n4. Laser cutting for shaping foams and tubes\n\n**PROCESS IMPROVEMENTS:**\n1. Simple immersion in water for efficient dissolution and recycling process\n2. Accessible recycling process without complicated tools or steps\n3. Reduced energy consumption due to screen printing requiring less expensive equipment and ecosystem\n\n**RELEVANCE TO PBT_Injection_Molding:**\nNo direct relevance to PBT_Injection_Molding. The paper studies recyclable electronics using PVA and LM, with no material overlap (paper materials: PVA and LM vs. hotspot materials: PBT). Process differences: paper examines screen printing, mechanical stirring, and mold casting vs. hotspot process: injection molding. Scale mismatch: the paper focuses on small-scale, low-quantity manufacturing, whereas injection molding is often used for large-scale production. No quantitative sustainability metrics directly applicable to this manufacturing hotspot's environmental impact reduction.",
        "has_quantitative_data": false
      },
      {
        "hotspot_name": "PBT_Injection_Molding",
        "paper_title": "Space debris through the prism of the environmental performance of space\n  systems: the case of Sentinel-3 redesigned mission",
        "paper_metadata": {
          "filename": "Space debris through the prism of the environmental performance of space systems.pdf",
          "hotspot_name": "PBT_Injection_Molding",
          "title": "Space debris through the prism of the environmental performance of space\n  systems: the case of Sentinel-3 redesigned mission",
          "published_date": "2022-07-13T15:58:25Z",
          "pdf_link": "http://arxiv.org/pdf/2207.06306v1",
          "query": "PBT injection molding LCA environmental impact"
        },
        "analysis_content": "**QUANTITATIVE FINDINGS:**\n- 6% higher specific impulse (Isp) of LMP-103s compared to Hydrazine\n- 24% higher density of LMP-103s in liquid form compared to Hydrazine\n- 2.3 times higher impact score for the baseline scenario (using Hydrazine) compared to the 'GreenSat' scenario (using LMP-103s) in terms of potential fragments-years generated\n- 36% of the impact comes from the utilization phase for the baseline scenario\n- 87% of the impact comes from the utilization phase for the 'GreenSat' scenario\n- 64% of the impact comes from the disposal phase for the baseline scenario\n- 25-35% contribution of the utilization stage to the environmental impacts for the overall categories, including space debris generation potential\n- 50% contribution of the detailed definition, qualification, and production stage to most of the impact categories\n- 100% contribution of the production of the PV system to the mineral resource depletion potential\n- 32% increase in the amount of propellant used in the 'GreenSat' scenario compared to the baseline scenario\n- 89 years duration of the disposal phase for the baseline scenario\n- 25 years duration of the disposal phase for the 'GreenSat' scenario\n\n**TECHNOLOGIES/METHODS:**\n- Life Cycle Assessment (LCA) methodology\n- Environmental Life Cycle Assessment (ELCA) framework\n- NASA break-up model\n- ESA's Space Debris Office's Debris Risk Assessment and Mitigation Analysis (DRAMA) software\n- OSCAR tool for propagating trajectories\n\n**PROCESS IMPROVEMENTS:**\n- Replacement of Hydrazine with LMP-103s as a propellant, resulting in a 2.3 times lower impact score\n- Optimization of the propulsion system for a controlled re-entry, aiming to comply with the casualty risk threshold required by space debris mitigation standards\n\n**RELEVANCE TO PBT_Injection_Molding:**\nNo direct relevance to PBT_Injection_Molding. The paper studies the environmental performance of space systems, specifically the Sentinel-3 mission, with no material overlap (paper materials: Hydrazine, LMP-103s vs. hotspot materials: PBT). Process differences: paper examines space mission design and propulsion systems vs. hotspot process: injection molding. Scale mismatch: the paper deals with space systems, while the hotspot is related to injection molding. No quantitative sustainability metrics applicable to this manufacturing hotspot's environmental impact reduction.",
        "has_quantitative_data": false
      },
      {
        "hotspot_name": "PBT_Injection_Molding",
        "paper_title": "The environmental value of transport infrastructure in the UK: an\n  EXIOBASE analysis",
        "paper_metadata": {
          "filename": "The environmental value of transport infrastructure in the UK_ an EXIOBASE analy.pdf",
          "hotspot_name": "PBT_Injection_Molding",
          "title": "The environmental value of transport infrastructure in the UK: an\n  EXIOBASE analysis",
          "published_date": "2025-04-26T11:33:03Z",
          "pdf_link": "http://arxiv.org/pdf/2504.20098v1",
          "query": "PBT injection molding LCA environmental impact"
        },
        "analysis_content": "**QUANTITATIVE FINDINGS:**\nNo explicit quantitative sustainability improvements related to PBT_Injection_Molding were found in the paper.\n\n**TECHNOLOGIES/METHODS:**\nThe paper discusses Life Cycle Assessment (LCA) methods, including process-based LCA and hybrid LCA (EXIOBASE), but does not provide specific technologies or methods related to PBT_Injection_Molding.\n\n**PROCESS IMPROVEMENTS:**\nNo specific process improvements related to PBT_Injection_Molding were found in the paper.\n\n**RELEVANCE TO PBT_Injection_Molding:**\nNo direct relevance to PBT_Injection_Molding. The paper studies the environmental value of transport infrastructure in the UK using EXIOBASE analysis, with no material overlap or process similarity to PBT_Injection_Molding. The paper's focus on transport infrastructure and its environmental impacts does not provide any quantitative sustainability metrics applicable to the PBT_Injection_Molding manufacturing hotspot's environmental impact reduction.\n\nSince no quantitative data is found, the final answer is:\n\"NO QUANTITATIVE SUSTAINABILITY DATA FOUND\"",
        "has_quantitative_data": false
      }
    ],
    "PCBA_Production": [
      {
        "hotspot_name": "PCBA_Production",
        "paper_title": "Recyclable vitrimer-based printed circuit board for circular electronics",
        "paper_metadata": {
          "filename": "Recyclable vitrimer-based printed circuit board for circular electronics.pdf",
          "hotspot_name": "PCBA_Production",
          "title": "Recyclable vitrimer-based printed circuit board for circular electronics",
          "published_date": "2023-08-24T01:34:50Z",
          "pdf_link": "http://arxiv.org/pdf/2308.12496v1",
          "query": "PCB assembly sustainability environmental assessment"
        },
        "analysis_content": "**QUANTITATIVE FINDINGS:**\n\n1. 98% recovery of the vitrimer polymer\n2. 100% recovery of glass fibers\n3. 91% recovery of the solvent (THF)\n4. 47.9% improvement in global warming potential\n5. 65.5% improvement in ozone depletion potential\n6. 80.9% improvement in human cancer toxicity emissions\n7. 35.8% reduction in acidification\n8. 59.1% reduction in freshwater ecotoxicity\n9. 61.8% reduction in human non-cancer toxicity emissions\n10. 38.0% reduction in particulate matter\n11. 45.9% reduction in photochemical ozone\n12. 40.2% reduction in fossil depletion\n13. 79.2% reduction in mineral and metal use\n14. 28.1% reduction in water use\n15. 20.0% reduction in global warming potential for vPCB freight\n16. 28.0% reduction in ozone depletion potential for vPCB freight\n17. 14.0% reduction in fossil depletion for vPCB freight\n18. 26.0% reduction in mineral and metal use for vPCB freight\n\n**TECHNOLOGIES/METHODS:**\n\n1. Vitrimer-based printed circuit board (vPCB) fabrication\n2. Transesterification vitrimer synthesis\n3. Swelling-based separation for vitrimer composite recycling\n4. Dynamic mechanical analysis\n5. Fourier-transform infrared (FTIR) spectroscopy\n\n**PROCESS IMPROVEMENTS:**\n\n1. Temperature optimization for vitrimer synthesis\n2. Pressure optimization for vitrimer synthesis\n3. Solvent selection for vitrimer recycling (THF)\n4. Recycling process for vPCB\n\n**RELEVANCE TO PCBA_Production:**\n\nThe paper's findings on vitrimer-based printed circuit board (vPCB) fabrication and recycling have direct relevance to the PCBA_Production hotspot. The use of vPCBs could reduce the environmental impact of PCBA production by:\n\n* Reducing energy consumption: The paper's findings on temperature optimization and solvent selection could lead to energy savings in the production process.\n* Reducing material waste: The paper's findings on 98% recovery of the vitrimer polymer and 100% recovery of glass fibers could reduce material waste in the production process.\n* Reducing environmental impact: The paper's findings on improvements in global warming potential, ozone depletion potential, and human cancer toxicity emissions could reduce the overall environmental impact of PCBA production.\n\nThe technology and methods used in the paper, such as vitrimer synthesis and swelling-based separation, could be directly applied to the PCBA_Production hotspot. However, further research would be needed to adapt these technologies to the specific materials and processes used in PCBA production.",
        "has_quantitative_data": true
      },
      {
        "hotspot_name": "PCBA_Production",
        "paper_title": "PCB Renewal: Iterative Reuse of PCB Substrates for Sustainable\n  Electronic Making",
        "paper_metadata": {
          "filename": "PCB Renewal_ Iterative Reuse of PCB Substrates for Sustainable Electronic Making.pdf",
          "hotspot_name": "PCBA_Production",
          "title": "PCB Renewal: Iterative Reuse of PCB Substrates for Sustainable\n  Electronic Making",
          "published_date": "2025-02-18T19:29:09Z",
          "pdf_link": "http://arxiv.org/pdf/2502.13255v1",
          "query": "PCB assembly sustainability environmental assessment"
        },
        "analysis_content": "**QUANTITATIVE FINDINGS:**\n\n1. 98.4% reduction in material cost for the first iteration of the camera roller PCB.\n2. 6402.90mg of FR-4 saved in the first iteration of the camera roller PCB.\n3. 71.91kJ of energy saved in the first iteration of the camera roller PCB.\n4. 15.25 minutes of fabrication time saved in the first iteration of the camera roller PCB.\n5. 4.06mg of silver epoxy consumed in the first iteration of the camera roller PCB.\n6. 74.6% reduction in material cost for the WiFi radio PCB.\n7. 5602.15mg of FR-4 saved in the WiFi radio PCB.\n8. 32.03kJ of energy saved in the WiFi radio PCB.\n9. 105mg of silver epoxy consumed in the WiFi radio PCB.\n10. 3.89 minutes longer fabrication time for the WiFi radio PCB compared to creating a new PCB.\n11. 87.5% reduction in material cost for the ESPBoy game console PCB.\n12. 5608.24mg of FR-4 saved in the ESPBoy game console PCB.\n13. 25.99kJ of energy saved in the ESPBoy game console PCB.\n14. 98.91mg of silver epoxy consumed in the ESPBoy game console PCB.\n15. Less than 5 minutes difference in fabrication time for the ESPBoy game console PCB compared to creating a new PCB.\n\n**TECHNOLOGIES/METHODS:**\n\n1. PCB Renewal technique for iterative reuse of PCB substrates.\n2. Conductive epoxy for filling isolation grooves and creating new conductive traces.\n3. CNC milling machine for engraving and modifying PCB substrates.\n4. Laser cutter for removing solder mask and creating deposition stencils.\n5. KiCAD software for designing and comparing PCB layouts.\n6. Custom EDA software plug-in for guiding epoxy deposition, generating updated profiles, and calculating resource usage.\n\n**PROCESS IMPROVEMENTS:**\n\n1. Reduced material waste through iterative reuse of PCB substrates.\n2. Decreased energy consumption by re-engraving existing PCB substrates instead of creating new ones.\n3. Improved fabrication efficiency by automating epoxy deposition and curing processes.\n4. Enhanced design flexibility through the ability to modify and update existing PCB layouts.\n\n**RELEVANCE TO PCBA_Production:**\n\nThe paper's findings on PCB Renewal and its applications in iterative reuse of PCB substrates have strong relevance to the PCBA_Production hotspot. The technique's ability to reduce material waste, energy consumption, and fabrication time can be directly applied to the production of printed circuit boards. The use of conductive epoxy and CNC milling machines can be adapted to various PCB production processes, including those used in PCBA_Production. The custom EDA software plug-in can also be integrated into existing design and manufacturing workflows to optimize resource usage and reduce environmental impact.\n\nThe quantitative benefits of PCB Renewal, such as the 98.4% reduction in material cost and 71.91kJ of energy saved, can be translated to the PCBA_Production hotspot by considering the material quantities and significance level of the production process. For example, if the hotspot produces 1000 PCBs per day, the application of PCB Renewal could potentially reduce material waste by 6402.90mg per PCB, resulting in a significant environmental impact reduction. Similarly, the energy savings of 71.91kJ per PCB could be scaled up to the entire production process, leading to substantial reductions in energy consumption and greenhouse gas emissions.",
        "has_quantitative_data": true
      },
      {
        "hotspot_name": "PCBA_Production",
        "paper_title": "Sustainable bioplastics from amyloid fibril-biodegradable polymer blends",
        "paper_metadata": {
          "filename": "Sustainable bioplastics from amyloid fibril-biodegradable polymer blends.pdf",
          "hotspot_name": "PCBA_Production",
          "title": "Sustainable bioplastics from amyloid fibril-biodegradable polymer blends",
          "published_date": "2021-05-29T12:49:57Z",
          "pdf_link": "http://arxiv.org/pdf/2105.14287v1",
          "query": "PCB assembly sustainability environmental assessment"
        },
        "analysis_content": "**QUANTITATIVE FINDINGS:**\n\n1. **Climate Change Impact Reduction**: 4.260198 kg CO2 eq per kg of HAm-PVA bioplastic produced, which is lower than PLA (9.220808 kg CO2 eq/kg) and PVF (16.65613 kg CO2 eq/kg).\n2. **Energy Consumption Reduction**: HAm-PVA bioplastic has 4 times lower energy consumption than PVF and 3 times lower than PLA.\n3. **Marine Ecotoxicity Reduction**: HAm-PVA bioplastic shows minimal marine ecotoxicity effect (0.02 kg 1,4-DB eq) compared to PLA (0.07 kg 1,4-DB eq) and PVF (0.16 kg 1,4-DB eq).\n4. **Water Depletion Reduction**: HAm-PVA bioplastic has lower water depletion impact (0.070116 m3) compared to PLA (0.322912 m3) and PVF (0.21498 m3).\n5. **Material Efficiency Improvement**: Amyloid-based films show improved mechanical properties, such as maximum stress (17 MPa) and toughness, compared to monomer-based films.\n\n**TECHNOLOGIES/METHODS:**\n\n1. **Bioplastic Production**: A simple, scalable, and water-based process to produce free-standing, transparent, and flexible bioplastic films by combining amyloid fibrils with biodegradable polymers.\n2. **Life Cycle Assessment (LCA)**: LCA was performed to evaluate the environmental impact of HAm-PVA bioplastic compared to PLA and PVF.\n\n**PROCESS IMPROVEMENTS:**\n\n1. **Temperature Optimization**: Heating the solution at 90Â°C for 5 hours to convert whey protein monomers to amyloid fibrils.\n2. **Plasticizer Addition**: Adding glycerol as a plasticizer to improve the mechanical properties of the bioplastic films.\n\n**RELEVANCE TO PCBA_Production:**\n\nNo direct relevance to PCBA_Production. The paper studies bioplastic production from amyloid fibril-biodegradable polymer blends, which does not overlap with the PCBA_Production process. The materials, processes, and scales are different, and no quantitative sustainability metrics are applicable to this manufacturing hotspot's environmental impact reduction.",
        "has_quantitative_data": false
      }
    ],
    "Steel_Punching_and_Bending": [
      {
        "hotspot_name": "Steel_Punching_and_Bending",
        "paper_title": "Anisotropic behaviour law for sheets used in stamping: A comparative\n  study of steel and aluminium",
        "paper_metadata": {
          "filename": "Anisotropic behaviour law for sheets used in stamping_ A comparative study of st.pdf",
          "hotspot_name": "Steel_Punching_and_Bending",
          "title": "Anisotropic behaviour law for sheets used in stamping: A comparative\n  study of steel and aluminium",
          "published_date": "2008-01-19T07:48:14Z",
          "pdf_link": "http://arxiv.org/pdf/0801.3018v1",
          "query": "steel punching bending LCA reduction"
        },
        "analysis_content": "**QUANTITATIVE FINDINGS:**\n- 30-40% reduction in weight can be expected when using aluminium instead of steel.\n\n**TECHNOLOGIES/METHODS:**\n- Stamping of thin aluminium sheets\n- Quadratic non-centered Hillâs (1948) yield criterion\n- Mixed hardening law (kinematic and isotropic)\n\n**PROCESS IMPROVEMENTS:**\n- None explicitly stated in terms of process improvements with measurable results.\n\n**RELEVANCE TO Steel_Punching_and_Bending:**\nThe paper's focus on the anisotropic behavior law for sheets used in stamping, comparing steel and aluminium, has some relevance to the Steel_Punching_and_Bending hotspot. \n\n1. **MATERIAL COMPATIBILITY ANALYSIS:**\n   - The paper studies steel and aluminium, which includes the material of interest for the Steel_Punching_and_Bending hotspot (steel).\n   - Steel is directly relevant, but the paper's primary focus on aluminium for weight reduction suggests a potential application in reducing the environmental impact of steel punching and bending by considering alternative materials.\n\n2. **PROCESS ALIGNMENT ASSESSMENT:**\n   - The manufacturing process investigated (stamping) is similar to punching and bending in terms of shaping metal sheets.\n   - However, the specific conditions (temperature, pressure, cycle times) are not directly compared or optimized in the paper for steel punching and bending.\n\n3. **QUANTITATIVE SUSTAINABILITY BENEFIT TRANSLATION:**\n   - The 30-40% weight reduction potential by using aluminium instead of steel could imply a significant reduction in material usage and potentially in energy consumption for processing, given that less material needs to be manipulated.\n   - However, this benefit is more directly applicable to scenarios where material substitution is feasible rather than optimizing the steel punching and bending process itself.\n\n4. **TECHNOLOGY AND METHOD ADAPTATION POTENTIAL:**\n   - The mixed hardening law and the quadratic non-centered Hillâs yield criterion could potentially be adapted for optimizing steel punching and bending processes, especially in understanding and predicting material behavior under different loading conditions.\n   - However, the paper does not provide a direct method for reducing energy consumption, waste, or environmental impact specifically in steel punching and bending.\n\nGiven the indirect application of the paper's findings to the Steel_Punching_and_Bending hotspot, the relevance is considered weak. The primary benefit discussed (weight reduction through material substitution) does not directly address process optimizations for steel punching and bending.",
        "has_quantitative_data": true
      },
      {
        "hotspot_name": "Steel_Punching_and_Bending",
        "paper_title": "475Â°C aging embrittlement of partially recrystallized FeCrAl ODS\n  ferritic steels after simulated tube process",
        "paper_metadata": {
          "filename": "475_C aging embrittlement of partially recrystallized FeCrAl ODS ferritic steels.pdf",
          "hotspot_name": "Steel_Punching_and_Bending",
          "title": "475Â°C aging embrittlement of partially recrystallized FeCrAl ODS\n  ferritic steels after simulated tube process",
          "published_date": "2023-10-20T22:31:18Z",
          "pdf_link": "http://arxiv.org/pdf/2310.13842v2",
          "query": "steel punching bending LCA reduction"
        },
        "analysis_content": "**QUANTITATIVE FINDINGS:**\n\n1. 30% reduction in total elongation in steels after full tubing routine compared to as-extruded ones.\n2. 25% to 50% reduction of yield stress after fully recrystallization.\n3. 50% thickness reduction in each cold rolling cycle.\n4. 100MPa reduction in yield stress of STPed SP2 compared to as-extruded steel.\n5. 2000 hrs and 10000 hrs aging times for the STPed steels.\n6. 475 Â°C aging temperature.\n7. 0.3 mm thickness of the STPed plates.\n8. 4 mm initial sample thickness.\n9. 1/3 reduction of ductility in the as-extruded steels after aging.\n\n**TECHNOLOGIES/METHODS:**\n\n1. Simulated tube processing (STP)\n2. Cold rolling and heat treatment (CR-HT)\n3. Transmission electron microscopy (TEM)\n4. Electron Back Scatter Diffraction (EBSD)\n5. Mechanical alloying method\n6. Uniaxial tensile test\n\n**PROCESS IMPROVEMENTS:**\n\n1. Recrystallization treatment to reduce yield strength of ODS steels during tubing.\n2. Optimization of composition of FeCrAl steels to satisfy both oxidation resistance and low aging rate.\n\n**RELEVANCE TO Steel_Punching_and_Bending:**\n\nThe paper's findings on the aging embrittlement of partially recrystallized FeCrAl ODS ferritic steels after simulated tube processing have limited direct relevance to the Steel_Punching_and_Bending hotspot. However, the study's focus on optimizing material properties and processing conditions to improve sustainability metrics (e.g., reducing energy consumption, increasing material efficiency) could be applied to the Steel_Punching_and_Bending process.\n\nMATERIAL COMPATIBILITY ANALYSIS:\nThe paper studies FeCrAl ODS ferritic steels, which may not be directly applicable to the Steel_Punching_and_Bending hotspot. However, the principles of optimizing material properties and processing conditions could be transferred to other steel alloys used in punching and bending operations.\n\nPROCESS ALIGNMENT ASSESSMENT:\nThe simulated tube processing and cold rolling techniques used in the paper may not be directly applicable to the Steel_Punching_and_Bending process. However, the study's focus on optimizing processing conditions (e.g., temperature, thickness reduction) could be relevant to improving the sustainability of punching and bending operations.\n\nQUANTITATIVE SUSTAINABILITY BENEFIT TRANSLATION:\nThe paper's findings on the reduction of total elongation and yield stress could be translated to potential energy savings and reduced material waste in the Steel_Punching_and_Bending process. However, the exact quantitative benefits would depend on the specific material properties and processing conditions used in the hotspot.\n\nTECHNOLOGY AND METHOD ADAPTATION POTENTIAL:\nThe optimization techniques used in the paper (e.g., recrystallization treatment, composition optimization) could be adapted to the Steel_Punching_and_Bending process. However, the feasibility of these adaptations would depend on the specific material properties and processing conditions used in the hotspot.",
        "has_quantitative_data": true
      },
      {
        "hotspot_name": "Steel_Punching_and_Bending",
        "paper_title": "Fast Privacy-Preserving Punch Cards",
        "paper_metadata": {
          "filename": "Fast Privacy-Preserving Punch Cards.pdf",
          "hotspot_name": "Steel_Punching_and_Bending",
          "title": "Fast Privacy-Preserving Punch Cards",
          "published_date": "2020-06-10T21:49:15Z",
          "pdf_link": "http://arxiv.org/pdf/2006.06079v3",
          "query": "steel punching bending LCA reduction"
        },
        "analysis_content": "**QUANTITATIVE FINDINGS:**\n1. 171Ã reduction in client-side computation required to generate a new punch card\n2. 14Ã reduction in total client and server computation times to perform a card punch\n3. 128Ã reduction in the computation time required to redeem a card\n4. 11Ã reduction in communication costs to punch a card\n5. 55Ã reduction in communication costs to redeem a card\n6. 13.9Ã faster punching a card compared to the best prior work (BBW)\n7. 127.9Ã faster redeeming a card compared to the best prior work (BBW)\n8. 10.9Ã reduction in communication for punching a card compared to the best prior work (BBA+ and BBW)\n9. 54.7Ã reduction in communication for redeeming a card compared to the best prior work (BBA+ and BBW)\n\n**TECHNOLOGIES/METHODS:**\n1. Curve25519-dalek for the main punch card scheme\n2. Pairing-plus (BLS12-381 curves) for the mergeable punch card scheme\n3. Chaum-Pedersen proof system for zero-knowledge proofs\n4. Random oracle model for hash functions\n\n**PROCESS IMPROVEMENTS:**\n1. Removal of reliance on pairings for improved performance\n2. Simplification of zero-knowledge proofs\n3. Optimization of computation and communication costs for punch card operations\n\n**RELEVANCE TO Steel_Punching_and_Bending:**\nNo direct relevance to Steel_Punching_and_Bending. The paper studies digital punch card loyalty programs with no material overlap (paper materials: none vs. hotspot materials: steel). Process differences: paper examines cryptographic protocols vs. hotspot process: steel punching and bending. Scale mismatch: the paper focuses on individual customer transactions vs. industrial-scale steel processing. No quantitative sustainability metrics applicable to this manufacturing hotspot's environmental impact reduction.",
        "has_quantitative_data": false
      }
    ]
  },
  "baseline_hotspot_analysis": {
    "production_hotspots": [
      {
        "hotspot_name": "PBT Injection Molding",
        "impact_category": "Material Extraction and Processing",
        "environmental_significance": "medium",
        "impact_source": "Housing production",
        "quantitative_impact": "37.45g PBT",
        "description": "The production of the housing component using PBT material through injection molding may have environmental impacts related to material extraction and processing."
      },
      {
        "hotspot_name": "Aluminium Die Casting",
        "impact_category": "Material Extraction and Processing",
        "environmental_significance": "high",
        "impact_source": "Radiator production",
        "quantitative_impact": "160.1g Aluminium",
        "description": "The production of the radiator component using aluminium material through die casting may have significant environmental impacts related to material extraction and processing."
      },
      {
        "hotspot_name": "PCBA Production",
        "impact_category": "Material Extraction and Processing",
        "environmental_significance": "medium",
        "impact_source": "PCBA production",
        "quantitative_impact": "40.7g PCB + 61.8g soldered components",
        "description": "The production of the PCBA component using various materials through THT and SMD soldering may have environmental impacts related to material extraction and processing."
      },
      {
        "hotspot_name": "Steel Punching and Bending",
        "impact_category": "Material Extraction and Processing",
        "environmental_significance": "low",
        "impact_source": "EMC Shield production",
        "quantitative_impact": "30.5g Steel",
        "description": "The production of the EMC Shield component using steel material through punching and bending may have relatively low environmental impacts related to material extraction and processing."
      }
    ],
    "distribution_hotspots": [],
    "use_hotspots": [],
    "end_of_life_hotspots": [],
    "overall_hotspot_ranking": [
      {
        "rank": 1,
        "hotspot_name": "Aluminium Die Casting",
        "life_cycle_phase": "production",
        "environmental_significance": "high",
        "priority_justification": "High weight of aluminium used in radiator production"
      },
      {
        "rank": 2,
        "hotspot_name": "PBT Injection Molding",
        "life_cycle_phase": "production",
        "environmental_significance": "medium",
        "priority_justification": "Medium weight of PBT used in housing production"
      },
      {
        "rank": 3,
        "hotspot_name": "PCBA Production",
        "life_cycle_phase": "production",
        "environmental_significance": "medium",
        "priority_justification": "Medium weight of materials used in PCBA production"
      },
      {
        "rank": 4,
        "hotspot_name": "Steel Punching and Bending",
        "life_cycle_phase": "production",
        "environmental_significance": "low",
        "priority_justification": "Low weight of steel used in EMC Shield production"
      }
    ]
  },
  "report_metadata": {
    "generation_timestamp": "2025-06-24 22:45:14",
    "total_hotspots_analyzed": 4,
    "total_papers_analyzed": 12,
    "papers_with_quantitative_data": 7,
    "papers_without_quantitative_data": 5
  }
}